<?xml version="1.0"?>

<workflow-definition
	xmlns="urn:liferay.com:liferay-workflow_7.4.0"
	xmlns:xsi="http://www.w3.org/2001/XMLSchema-instance"
	xsi:schemaLocation="urn:liferay.com:liferay-workflow_7.4.0 http://www.liferay.com/dtd/liferay-workflow-definition_7_4_0.xsd"
>
	<version>1</version>
	<state>
		<name>7cc1ce8f-188a-4b03-9610-b8fa64755e3c</name>
		<description>Begin a workflow.</description>
		<metadata>
			<![CDATA[
				{
					"xy": [
						48.00006103515625,
						125.00000762939453
					]
				}
			]]>
		</metadata>
		<actions>
			<action>
				<name>Pay</name>
				<description></description>
				<script>
					<![CDATA[
						import com.liferay.object.model.ObjectDefinition;
						import com.liferay.object.model.ObjectEntry;
						import com.liferay.object.service.ObjectDefinitionLocalServiceUtil;
						import com.liferay.object.service.ObjectEntryLocalServiceUtil;
						import com.liferay.portal.kernel.service.UserLocalServiceUtil;
						import com.liferay.portal.kernel.util.GetterUtil;
						import com.liferay.portal.kernel.workflow.WorkflowConstants;
						import com.liferay.portal.kernel.workflow.WorkflowStatusManagerUtil;

						import java.io.Serializable;

						import java.util.Map;

						long classPK = GetterUtil.getLong((String) workflowContext.get(
						WorkflowConstants.CONTEXT_ENTRY_CLASS_PK));

						ObjectEntry currentObjectEntry = ObjectEntryLocalServiceUtil.getObjectEntry(classPK);

						Map < String, Serializable > currentObjectEntryValues = currentObjectEntry.getValues();

						long requestId = currentObjectEntryValues.get("r_requestId_c_evpRequestId");

						ObjectEntry evpRequestObjectEntry = ObjectEntryLocalServiceUtil.getObjectEntry(requestId);

						Map < String, Serializable > evpRequestObjectEntryValues = evpRequestObjectEntry.getValues();

						evpRequestObjectEntryValues.put("requestStatus", "closed");

						ObjectEntryLocalServiceUtil.updateObjectEntry(serviceContext.getUserId(), requestId, evpRequestObjectEntryValues, serviceContext);
					]]>
				</script>
				<script-language>groovy</script-language>
				<priority>1</priority>
				<execution-type>onEntry</execution-type>
			</action>
		</actions>
		<initial>true</initial>
		<labels>
			<label language-id="en_US">
				Start
			</label>
		</labels>
		<transitions>
			<transition>
				<labels>
					<label language-id="en_US">
						Payment Done
					</label>
				</labels>
				<name>4eeb7589-9cf9-42d8-aafe-3c0e50c4d245</name>
				<target>044313bf-0751-4201-af13-e25264b0bea5</target>
				<default>true</default>
			</transition>
		</transitions>
	</state>
	<state>
		<name>044313bf-0751-4201-af13-e25264b0bea5</name>
		<description>Conclude the workflow.</description>
		<metadata>
			<![CDATA[
				{
					"terminal": true,
					"xy": [
						654.0000610351562,
						123.00003814697266
					]
				}
			]]>
		</metadata>
		<actions>
			<action>
				<name>Update Object Status</name>
				<description></description>
				<status>0</status>
				<priority>1</priority>
				<execution-type>onEntry</execution-type>
			</action>
			<notification>
				<name>Payment Notification</name>
				<description>
					<![CDATA[]]>
				</description>
				<template>
					<![CDATA[User ${userName} fex ID payment ${entryClassPK}]]>
				</template>
				<template-language>freemarker</template-language>
				<notification-type>user-notification</notification-type>
				<recipients receptionType="to">
					<roles>
						<role>
							<role-id>"[#ROLE_ID:Finance User#]"</role-id>
						</role>
					</roles>
				</recipients>
				<execution-type>onEntry</execution-type>
			</notification>
		</actions>
		<labels>
			<label language-id="en_US">
				End
			</label>
		</labels>
	</state>
</workflow-definition>